LICENSE
MANIFEST.in
README.rst
ez_setup.py
setup.py
riskiq/__init__.py
riskiq/api.py
riskiq/blacklist_stix.py
riskiq/config.py
riskiq/output.py
riskiq/render.py
riskiq.egg-info/PKG-INFO
riskiq.egg-info/SOURCES.txt
riskiq.egg-info/dependency_links.txt
riskiq.egg-info/entry_points.txt
riskiq.egg-info/not-zip-safe
riskiq.egg-info/requires.txt
riskiq.egg-info/top_level.txt
riskiq/cli/__init__.py
riskiq/cli/binary.py
riskiq/cli/config.py
riskiq/cli/dns.py
riskiq/cli/landingpage.py
riskiq/cli/mobile.py
riskiq/cli/parser.py
riskiq/cli/pdns.py
riskiq/cli/tests.py
riskiq/cli/util.py
riskiq/cli/whois.py
riskiq/cli/zlist.py
riskiq/cli/blacklist/__init__.py
riskiq/cli/blacklist/bl_list.py
riskiq/cli/blacklist/incident.py
riskiq/cli/blacklist/incidentlist.py
riskiq/cli/blacklist/lookup.py
riskiq/cli/blacklist/malware.py
riskiq/templates/blacklist/incident
riskiq/templates/blacklist/incident_oneline
riskiq/templates/blacklist/incidentlist
riskiq/templates/blacklist/incidentlist_oneline
riskiq/templates/blacklist/lookup
riskiq/templates/blacklist/lookup_oneline
riskiq/templates/blacklist/malware
riskiq/templates/blacklist/malware_oneline
riskiq/templates/dns/dns
riskiq/templates/dns/dns_data
riskiq/templates/dns/dns_name
riskiq/templates/dns/dns_oneline
riskiq/templates/landingpage/bulk
riskiq/templates/landingpage/crawled
riskiq/templates/landingpage/projects
riskiq/templates/whois/whois
riskiq/templates/zlist/urls