Metadata-Version: 1.1
Name: riskiq
Version: 0.4.8
Summary: client for RiskIQ REST API
Home-page: https://github.com/riskiq/python_api
Author: Research Team, RiskIQ
Author-email: research@riskiq.net
License: GPLv2
Keywords: riskiq API REST
Platform: UNKNOWN
Classifier: Development Status :: 4 - Beta
